[
  {
    "PLAYER_ID": 101108,
    "PLAYER_NAME": "Chris Paul",
    "TEAM_ID": 1610612759,
    "TEAM_ABBREVIATION": "SAS",
    "AGE": 39,
    "POS": "PG",
    "GP": 82,
    "GS": 82,
    "MIN": 2292,
    "PER": 14.7,
    "TS_PCT": 0.580,
    "3PAr": 0.636,
    "FTr": 0.158,
    "ORB_PCT": 1.5,
    "DRB_PCT": 12.3,
    "TRB_PCT": 6.9,
    "AST_PCT": 34.8,
    "STL_PCT": 2.2,
    "BLK_PCT": 0.9,
    "TOV_PCT": 17.1,
    "USG_PCT": 14.0,
    "OWS": 4.2,
    "DWS": 1.6,
    "WS": 5.7,
    "WS_48": 0.120,
    "OBPM": 0.3,
    "DBPM": 0.5,
    "PLUS_MINUS": 0.8,
    "VORP": 1.6
  },
  {
    "PLAYER_ID": 203084,
    "PLAYER_NAME": "Harrison Barnes",
    "TEAM_ID": 1610612759,
    "TEAM_ABBREVIATION": "SAS",
    "AGE": 32,
    "POS": "PF",
    "GP": 82,
    "GS": 82,
    "MIN": 2230,
    "PER": 14.9,
    "TS_PCT": 0.656,
    "3PAr": 0.527,
    "FTr": 0.291,
    "ORB_PCT": 4.7,
    "DRB_PCT": 10.3,
    "TRB_PCT": 7.4,
    "AST_PCT": 8.6,
    "STL_PCT": 0.8,
    "BLK_PCT": 0.6,
    "TOV_PCT": 6.1,
    "USG_PCT": 15.7,
    "OWS": 5.0,
    "DWS": 0.5,
    "WS": 5.6,
    "WS_48": 0.120,
    "OBPM": 1.7,
    "DBPM": -1.7,
    "PLUS_MINUS": 0.0,
    "VORP": 1.2
  },
  {
    "PLAYER_ID": 1642264,
    "PLAYER_NAME": "Stephon Castle",
    "TEAM_ID": 1610612759,
    "TEAM_ABBREVIATION": "SAS",
    "AGE": 20,
    "POS": "PG",
    "GP": 81,
    "GS": 47,
    "MIN": 2162,
    "PER": 13.7,
    "TS_PCT": 0.522,
    "3PAr": 0.337,
    "FTr": 0.348,
    "ORB_PCT": 4.4,
    "DRB_PCT": 10.3,
    "TRB_PCT": 7.4,
    "AST_PCT": 22.8,
    "STL_PCT": 1.7,
    "BLK_PCT": 0.9,
    "TOV_PCT": 13.4,
    "USG_PCT": 26.0,
    "OWS": 0.1,
    "DWS": 1.0,
    "WS": 1.1,
    "WS_48": 0.025,
    "OBPM": -1.5,
    "DBPM": -1.7,
    "PLUS_MINUS": -3.2,
    "VORP": -0.6
  },
  {
    "PLAYER_ID": 1630170,
    "PLAYER_NAME": "Devin Vassell",
    "TEAM_ID": 1610612759,
    "TEAM_ABBREVIATION": "SAS",
    "AGE": 24,
    "POS": "SG",
    "GP": 64,
    "GS": 53,
    "MIN": 1983,
    "PER": 14.2,
    "TS_PCT": 0.553,
    "3PAr": 0.483,
    "FTr": 0.135,
    "ORB_PCT": 1.8,
    "DRB_PCT": 12.0,
    "TRB_PCT": 6.9,
    "AST_PCT": 13.8,
    "STL_PCT": 2.0,
    "BLK_PCT": 1.5,
    "TOV_PCT": 8.5,
    "USG_PCT": 22.1,
    "OWS": 0.9,
    "DWS": 1.3,
    "WS": 2.2,
    "WS_48": 0.054,
    "OBPM": -0.3,
    "DBPM": -0.8,
    "PLUS_MINUS": -1.1,
    "VORP": 0.4
  },
  {
    "PLAYER_ID": 1630577,
    "PLAYER_NAME": "Julian Champagnie",
    "TEAM_ID": 1610612759,
    "TEAM_ABBREVIATION": "SAS",
    "AGE": 23,
    "POS": "SF",
    "GP": 82,
    "GS": 29,
    "MIN": 1932,
    "PER": 12.2,
    "TS_PCT": 0.577,
    "3PAr": 0.722,
    "FTr": 0.141,
    "ORB_PCT": 3.7,
    "DRB_PCT": 13.9,
    "TRB_PCT": 8.8,
    "AST_PCT": 7.9,
    "STL_PCT": 1.5,
    "BLK_PCT": 1.6,
    "TOV_PCT": 9.5,
    "USG_PCT": 17.2,
    "OWS": 1.3,
    "DWS": 1.2,
    "WS": 2.5,
    "WS_48": 0.062,
    "OBPM": -0.3,
    "DBPM": -0.9,
    "PLUS_MINUS": -1.3,
    "VORP": 0.4
  },
  {
    "PLAYER_ID": 1629640,
    "PLAYER_NAME": "Keldon Johnson",
    "TEAM_ID": 1610612759,
    "TEAM_ABBREVIATION": "SAS",
    "AGE": 25,
    "POS": "SF",
    "GP": 77,
    "GS": 0,
    "MIN": 1838,
    "PER": 15.6,
    "TS_PCT": 0.572,
    "3PAr": 0.356,
    "FTr": 0.252,
    "ORB_PCT": 6.5,
    "DRB_PCT": 15.1,
    "TRB_PCT": 10.8,
    "AST_PCT": 10.2,
    "STL_PCT": 1.3,
    "BLK_PCT": 1.1,
    "TOV_PCT": 8.3,
    "USG_PCT": 21.6,
    "OWS": 2.2,
    "DWS": 1.0,
    "WS": 3.2,
    "WS_48": 0.083,
    "OBPM": 0.0,
    "DBPM": -1.6,
    "PLUS_MINUS": -1.6,
    "VORP": 0.2
  },
  {
    "PLAYER_ID": 1641705,
    "PLAYER_NAME": "Victor Wembanyama",
    "TEAM_ID": 1610612759,
    "TEAM_ABBREVIATION": "SAS",
    "AGE": 21,
    "POS": "C",
    "GP": 46,
    "GS": 46,
    "MIN": 1527,
    "PER": 24.2,
    "TS_PCT": 0.594,
    "3PAr": 0.470,
    "FTr": 0.221,
    "ORB_PCT": 5.7,
    "DRB_PCT": 29.8,
    "TRB_PCT": 17.7,
    "AST_PCT": 18.3,
    "STL_PCT": 1.6,
    "BLK_PCT": 10.4,
    "TOV_PCT": 13.7,
    "USG_PCT": 30.4,
    "OWS": 1.0,
    "DWS": 2.8,
    "WS": 3.8,
    "WS_48": 0.118,
    "OBPM": 3.6,
    "DBPM": 2.9,
    "PLUS_MINUS": 6.5,
    "VORP": 3.3
  },
  {
    "PLAYER_ID": 1631110,
    "PLAYER_NAME": "Jeremy Sochan",
    "TEAM_ID": 1610612759,
    "TEAM_ABBREVIATION": "SAS",
    "AGE": 21,
    "POS": "PF",
    "GP": 54,
    "GS": 23,
    "MIN": 1364,
    "PER": 15.9,
    "TS_PCT": 0.589,
    "3PAr": 0.194,
    "FTr": 0.267,
    "ORB_PCT": 10.0,
    "DRB_PCT": 17.7,
    "TRB_PCT": 13.8,
    "AST_PCT": 13.7,
    "STL_PCT": 1.6,
    "BLK_PCT": 1.8,
    "TOV_PCT": 13.8,
    "USG_PCT": 19.0,
    "OWS": 1.7,
    "DWS": 1.1,
    "WS": 2.7,
    "WS_48": 0.096,
    "OBPM": -0.8,
    "DBPM": -0.4,
    "PLUS_MINUS": -1.2,
    "VORP": 0.3
  },
  {
    "PLAYER_ID": 1631104,
    "PLAYER_NAME": "Blake Wesley",
    "TEAM_ID": 1610612759,
    "TEAM_ABBREVIATION": "SAS",
    "AGE": 21,
    "POS": "SG",
    "GP": 58,
    "GS": 0,
    "MIN": 683,
    "PER": 9.9,
    "TS_PCT": 0.510,
    "3PAr": 0.312,
    "FTr": 0.328,
    "ORB_PCT": 2.7,
    "DRB_PCT": 6.9,
    "TRB_PCT": 4.8,
    "AST_PCT": 22.3,
    "STL_PCT": 2.6,
    "BLK_PCT": 0.8,
    "TOV_PCT": 20.2,
    "USG_PCT": 16.7,
    "OWS": -0.3,
    "DWS": 0.4,
    "WS": 0.2,
    "WS_48": 0.011,
    "OBPM": -3.9,
    "DBPM": -0.3,
    "PLUS_MINUS": -4.2,
    "VORP": -0.4
  },
  {
    "PLAYER_ID":1630572,
    "PLAYER_NAME": "Sandro Mamukelashvili",
    "TEAM_ID": 1610612759,
    "TEAM_ABBREVIATION": "SAS",
    "AGE": 25,
    "POS": "PF",
    "GP": 61,
    "GS": 0,
    "MIN": 681,
    "PER": 19.7,
    "TS_PCT": 0.628,
    "3PAr": 0.573,
    "FTr": 0.206,
    "ORB_PCT": 9.7,
    "DRB_PCT": 19.7,
    "TRB_PCT": 14.7,
    "AST_PCT": 10.7,
    "STL_PCT": 1.6,
    "BLK_PCT": 2.3,
    "TOV_PCT": 7.8,
    "USG_PCT": 20.8,
    "OWS": 1.6,
    "DWS": 0.6,
    "WS": 2.2,
    "WS_48": 0.152,
    "OBPM": 3.3,
    "DBPM": -1.0,
    "PLUS_MINUS": 2.3,
    "VORP": 0.7
  },
  {
    "PLAYER_ID": 1628368,
    "PLAYER_NAME": "De'Aaron Fox",
    "TEAM_ID": 1610612759,
    "TEAM_ABBREVIATION": "SAS",
    "AGE": 27,
    "POS": "PG",
    "GP": 17,
    "GS": 17,
    "MIN": 578,
    "PER": 16.3,
    "TS_PCT": 0.537,
    "3PAr": 0.339,
    "FTr": 0.257,
    "ORB_PCT": 1.7,
    "DRB_PCT": 11.9,
    "TRB_PCT": 6.8,
    "AST_PCT": 30.8,
    "STL_PCT": 2.1,
    "BLK_PCT": 0.8,
    "TOV_PCT": 11.6,
    "USG_PCT": 26.0,
    "OWS": 0.5,
    "DWS": 0.4,
    "WS": 0.9,
    "WS_48": 0.071,
    "OBPM": -0.6,
    "DBPM": -1.4,
    "PLUS_MINUS": -2.0,
    "VORP": 0.0
  },
  {
    "PLAYER_ID": 202687,
    "PLAYER_NAME": "Bismack Biyombo",
    "TEAM_ID": 1610612759,
    "TEAM_ABBREVIATION": "SAS",
    "AGE": 32,
    "POS": "C",
    "GP": 28,
    "GS": 26,
    "MIN": 528,
    "PER": 12.2,
    "TS_PCT": 0.576,
    "3PAr": 0.000,
    "FTr": 0.219,
    "ORB_PCT": 8.7,
    "DRB_PCT": 23.4,
    "TRB_PCT": 16.0,
    "AST_PCT": 7.9,
    "STL_PCT": 1.5,
    "BLK_PCT": 3.9,
    "TOV_PCT": 17.8,
    "USG_PCT": 12.3,
    "OWS": 0.2,
    "DWS": 0.6,
    "WS": 0.8,
    "WS_48": 0.071,
    "OBPM": -3.6,
    "DBPM": 0.0,
    "PLUS_MINUS": -3.6,
    "VORP": -0.2
  },
  {
    "PLAYER_ID": 1630200,
    "PLAYER_NAME": "Tre Jones",
    "TEAM_ID": 1610612759,
    "TEAM_ABBREVIATION": "SAS",
    "AGE": 25,
    "POS": "PG",
    "GP": 28,
    "GS": 0,
    "MIN": 450,
    "PER": 13.8,
    "TS_PCT": 0.572,
    "3PAr": 0.280,
    "FTr": 0.355,
    "ORB_PCT": 3.6,
    "DRB_PCT": 10.3,
    "TRB_PCT": 6.9,
    "AST_PCT": 30.1,
    "STL_PCT": 1.9,
    "BLK_PCT": 1.0,
    "TOV_PCT": 16.3,
    "USG_PCT": 12.2,
    "OWS": 0.9,
    "DWS": 0.3,
    "WS": 1.1,
    "WS_48": 0.118,
    "OBPM": -1.2,
    "DBPM": 1.1,
    "PLUS_MINUS": -0.1,
    "VORP": 0.2
  },
  {
    "PLAYER_ID": 1631103,
    "PLAYER_NAME": "Malaki Branham",
    "TEAM_ID": 1610612759,
    "TEAM_ABBREVIATION": "SAS",
    "AGE": 21,
    "POS": "SG",
    "GP": 47,
    "GS": 0,
    "MIN": 427,
    "PER": 12.0,
    "TS_PCT": 0.575,
    "3PAr": 0.442,
    "FTr": 0.174,
    "ORB_PCT": 1.8,
    "DRB_PCT": 11.1,
    "TRB_PCT": 6.4,
    "AST_PCT": 13.4,
    "STL_PCT": 1.2,
    "BLK_PCT": 0.4,
    "TOV_PCT": 14.3,
    "USG_PCT": 23.8,
    "OWS": -0.1,
    "DWS": 0.2,
    "WS": 0.1,
    "WS_48": 0.007,
    "OBPM": -1.2,
    "DBPM": -1.9,
    "PLUS_MINUS": -3.2,
    "VORP": -0.1
  },
  {
    "PLAYER_ID": 1628380,
    "PLAYER_NAME": "Zach Collins",
    "TEAM_ID": 1610612759,
    "TEAM_ABBREVIATION": "SAS",
    "AGE": 27,
    "POS": "C",
    "GP": 36,
    "GS": 4,
    "MIN": 425,
    "PER": 14.4,
    "TS_PCT": 0.566,
    "3PAr": 0.348,
    "FTr": 0.265,
    "ORB_PCT": 9.6,
    "DRB_PCT": 15.9,
    "TRB_PCT": 12.7,
    "AST_PCT": 16.9,
    "STL_PCT": 1.6,
    "BLK_PCT": 3.2,
    "TOV_PCT": 13.5,
    "USG_PCT": 17.1,
    "OWS": 0.6,
    "DWS": 0.4,
    "WS": 1.0,
    "WS_48": 0.110,
    "OBPM": -1.6,
    "DBPM": 1.5,
    "PLUS_MINUS": -0.1,
    "VORP": 0.2
  },
  {
    "PLAYER_ID": 1629646,
    "PLAYER_NAME": "Charles Bassey",
    "TEAM_ID": 1610612759,
    "TEAM_ABBREVIATION": "SAS",
    "AGE": 24,
    "POS": "C",
    "GP": 36,
    "GS": 1,
    "MIN": 376,
    "PER": 19.0,
    "TS_PCT": 0.597,
    "3PAr": 0.000,
    "FTr": 0.282,
    "ORB_PCT": 15.9,
    "DRB_PCT": 27.4,
    "TRB_PCT": 21.7,
    "AST_PCT": 6.6,
    "STL_PCT": 1.8,
    "BLK_PCT": 7.2,
    "TOV_PCT": 14.9,
    "USG_PCT": 17.5,
    "OWS": 0.5,
    "DWS": 0.6,
    "WS": 1.1,
    "WS_48": 0.136,
    "OBPM": -1.7,
    "DBPM": 0.6,
    "PLUS_MINUS": -1.1,
    "VORP": 0.1
  },
  {
    "PLAYER_ID": 1629162,
    "PLAYER_NAME": "Jordan McLaughlin",
    "TEAM_ID": 1610612759,
    "TEAM_ABBREVIATION": "SAS",
    "AGE": 28,
    "POS": "PG",
    "GP": 18,
    "GS": 0,
    "MIN": 124,
    "PER": 16.9,
    "TS_PCT": 0.734,
    "3PAr": 0.714,
    "FTr": 0.214,
    "ORB_PCT": 1.7,
    "DRB_PCT": 6.1,
    "TRB_PCT": 3.9,
    "AST_PCT": 29.1,
    "STL_PCT": 1.9,
    "BLK_PCT": 0.7,
    "TOV_PCT": 14.0,
    "USG_PCT": 12.3,
    "OWS": 0.4,
    "DWS": 0.0,
    "WS": 0.5,
    "WS_48": 0.178,
    "OBPM": 1.8,
    "DBPM": -0.5,
    "PLUS_MINUS": 1.3,
    "VORP": 0.1
  },
  {
    "PLAYER_ID": 1631321,
    "PLAYER_NAME": "Sidy Cissoko",
    "TEAM_ID": 1610612759,
    "TEAM_ABBREVIATION": "SAS",
    "AGE": 20,
    "POS": "SF",
    "GP": 17,
    "GS": 0,
    "MIN": 54,
    "PER": 11.2,
    "TS_PCT": 0.533,
    "3PAr": 0.389,
    "FTr": 0.333,
    "ORB_PCT": 5.9,
    "DRB_PCT": 13.9,
    "TRB_PCT": 9.9,
    "AST_PCT": 15.8,
    "STL_PCT": 0.9,
    "BLK_PCT": 0.0,
    "TOV_PCT": 8.8,
    "USG_PCT": 17.9,
    "OWS": 0.0,
    "DWS": 0.0,
    "WS": 0.0,
    "WS_48": 0.041,
    "OBPM": -1.6,
    "DBPM": -1.0,
    "PLUS_MINUS": -2.6,
    "VORP": 0.0
  },
  {
    "PLAYER_ID": 1631127,
    "PLAYER_NAME": "Harrison Ingram",
    "TEAM_ID": 1610612759,
    "TEAM_ABBREVIATION": "SAS",
    "AGE": 22,
    "POS": "SF",
    "GP": 5,
    "GS": 0,
    "MIN": 35,
    "PER": 10.9,
    "TS_PCT": 0.500,
    "3PAr": 0.250,
    "FTr": 0.000,
    "ORB_PCT": 6.1,
    "DRB_PCT": 21.5,
    "TRB_PCT": 13.8,
    "AST_PCT": 10.6,
    "STL_PCT": 4.1,
    "BLK_PCT": 0.0,
    "TOV_PCT": 20.0,
    "USG_PCT": 6.1,
    "OWS": 0.0,
    "DWS": 0.1,
    "WS": 0.1,
    "WS_48": 0.093,
    "OBPM": -3.6,
    "DBPM": 2.4,
    "PLUS_MINUS": -1.2,
    "VORP": 0.0
  },
  {
    "PLAYER_ID":1630561,
    "PLAYER_NAME": "David Duke Jr.",
    "TEAM_ID": 1610612759,
    "TEAM_ABBREVIATION": "SAS",
    "AGE": 25,
    "POS": "SG",
    "GP": 6,
    "GS": 0,
    "MIN": 34,
    "PER": 12.2,
    "TS_PCT": 0.538,
    "3PAr": 0.429,
    "FTr": 0.143,
    "ORB_PCT": 3.1,
    "DRB_PCT": 12.6,
    "TRB_PCT": 7.9,
    "AST_PCT": 17.0,
    "STL_PCT": 1.4,
    "BLK_PCT": 0.0,
    "TOV_PCT": 11.8,
    "USG_PCT": 21.2,
    "OWS": 0.0,
    "DWS": 0.0,
    "WS": 0.0,
    "WS_48": 0.023,
    "OBPM": -0.1,
    "DBPM": -1.4,
    "PLUS_MINUS": -1.5,
    "VORP": 0.0
  },
  {
    "PLAYER_ID": 1642434,
    "PLAYER_NAME": "Riley Minix",
    "TEAM_ID": 1610612759,
    "TEAM_ABBREVIATION": "SAS",
    "AGE": 24,
    "POS": "SF",
    "GP": 1,
    "GS": 0,
    "MIN": 7,
    "PER": -1.7,
    "TS_PCT": 0.000,
    "3PAr": 1.000,
    "FTr": 0.000,
    "ORB_PCT": 0.0,
    "DRB_PCT": 30.7,
    "TRB_PCT": 15.3,
    "AST_PCT": 0.0,
    "STL_PCT": 0.0,
    "BLK_PCT": 0.0,
    "TOV_PCT": 0.0,
    "USG_PCT": 6.1,
    "OWS": 0.0,
    "DWS": 0.0,
    "WS": 0.0,
    "WS_48": -0.114,
    "OBPM": -8.5,
    "DBPM": -3.3,
    "PLUS_MINUS": -11.8,
    "VORP": 0.0
  }
]